pyccapt/__init__.py
pyccapt/calibration/__init__.py
pyccapt/calibration/calibration/__init__.py
pyccapt/calibration/calibration/calibration.py
pyccapt/calibration/calibration/gui_ion_select.py
pyccapt/calibration/calibration/hist_bin_optimizer.py
pyccapt/calibration/calibration/intractive_point_identification.py
pyccapt/calibration/calibration/ion_selection.py
pyccapt/calibration/calibration/logging_library.py
pyccapt/calibration/calibration/mc_plot.py
pyccapt/calibration/calibration/share_variables.py
pyccapt/calibration/calibration/tools.py
pyccapt/calibration/calibration/widgets.py
pyccapt/calibration/clustering/__init__.py
pyccapt/calibration/clustering/clustering.py
pyccapt/calibration/clustering/isosurface.py
pyccapt/calibration/data_tools/__init__.py
pyccapt/calibration/data_tools/ato_tools.py
pyccapt/calibration/data_tools/data_loadcrop.py
pyccapt/calibration/data_tools/data_tools.py
pyccapt/calibration/data_tools/dataset_path_qt.py
pyccapt/calibration/data_tools/merge_range.py
pyccapt/calibration/data_tools/plot_vline_draw.py
pyccapt/calibration/data_tools/raw_data_surface_concept.py
pyccapt/calibration/data_tools/run_dataset_path_qt.py
pyccapt/calibration/data_tools/selectors_data.py
pyccapt/calibration/leap_tools/__init__.py
pyccapt/calibration/leap_tools/ccapt_tools.py
pyccapt/calibration/leap_tools/cloud_ploter.py
pyccapt/calibration/leap_tools/leap_tools.py
pyccapt/calibration/mc/__init__.py
pyccapt/calibration/mc/mc_tools.py
pyccapt/calibration/mc/tof_tools.py
pyccapt/calibration/reconstructions/__init__.py
pyccapt/calibration/reconstructions/crystal_helper.py
pyccapt/calibration/reconstructions/density_map.py
pyccapt/calibration/reconstructions/fft.py
pyccapt/calibration/reconstructions/iso_surface.py
pyccapt/calibration/reconstructions/rdf.py
pyccapt/calibration/reconstructions/reconstruction.py
pyccapt/calibration/reconstructions/sdm.py
pyccapt/calibration/tutorials/__init__.py
pyccapt/calibration/tutorials/tutorials_helpers/__init__.py
pyccapt-0.1.11.dist-info/LICENSE
pyccapt-0.1.11.dist-info/METADATA
pyccapt-0.1.11.dist-info/WHEEL
pyccapt-0.1.11.dist-info/entry_points.txt
pyccapt-0.1.11.dist-info/top_level.txt
pyccapt-0.1.11.dist-info/RECORD
