Metadata-Version: 2.1
Name: pyccapt
Version: 0.1.11
Summary: A package for controlling APT experiment and calibrating the APT data
Home-page: https://github.com/mmonajem/pyccapt
Author: Mehrpad Monajem
Author-email: mehrpad.monajem@fau.de
License: GPL v3
Platform: ALL
Classifier: Operating System :: Microsoft :: Windows
Classifier: Programming Language :: Python :: 3
Classifier: Topic :: Scientific/Engineering :: Visualization
Classifier: Intended Audience :: Science/Research
Requires-Python: >=3.9
License-File: LICENSE
Requires-Dist: opencv-python
Requires-Dist: networkx
Requires-Dist: pyqt6-tools
Requires-Dist: pyqtgraph
Requires-Dist: nidaqmx
Requires-Dist: pypylon
Requires-Dist: pyvisa
Requires-Dist: pyserial
Requires-Dist: deepdiff
Requires-Dist: scipy
Requires-Dist: h5py
Requires-Dist: tables
Requires-Dist: mcculw
Requires-Dist: simple-pid
Requires-Dist: ipywidgets
Requires-Dist: ipympl
Requires-Dist: scikit-learn
Requires-Dist: vispy
Requires-Dist: plotly
Requires-Dist: faker
Requires-Dist: nodejs
Requires-Dist: adjustText
Requires-Dist: pybaselines
Requires-Dist: kaleido
Requires-Dist: pymatgen
Requires-Dist: ase
Requires-Dist: imageio
Requires-Dist: nglview
Requires-Dist: jupyterlab
Requires-Dist: tqdm
Requires-Dist: fast-histogram
Requires-Dist: pyvista
Requires-Dist: numpy
Requires-Dist: matplotlib
Requires-Dist: pandas
Requires-Dist: PyQt6
Requires-Dist: numba
Requires-Dist: requests
Requires-Dist: wget
